Workbook

Sheet City Scoring Data
A1: Relocation Intelligence Dashboard — Weighted Family Scoring Framework
A2: Scores 1–10 (10 = best). Safety & Family Security weighted at 25% — family's #1 priority. Healthcare at 15% — reflects pediatric specialty access needs.
A4: City | B4: Safety & Family Security | C4: Healthcare Access | D4: Median Rent ($) | E4: School Rating | F4: Job Market | G4: Cost of Living | H4: Remote Work Culture | I4: Weather Risk | J4: Cultural Fit | K4: Weighted Score | L4: Rank
A5: Weight → | B5: 0.25 | C5: 0.15 | D5: 0.1 | E5: 0.1 | F5: 0.08 | G5: 0.1 | H5: 0.08 | I5: 0.07 | J5: 0.07
A6: Dallas-Fort Worth, TX | B6: 6 | C6: 8 | D6: 1850 | E6: 7 | F6: 9 | G6: 6 | H6: 8 | I6: 5 | J6: 7 | K6: =ROUND(($B6*B$5)+($C6*C$5)+((10-(($D6-MIN($D$6:$D$16))/(MAX($D$6:$D$16)-MIN($D$6:$D$16))*9))*D$5)+($E6*E$5)+($F6*F$5)+((11-$G6)*G$5)+($H6*H$5)+($I6*I$5)+($J6*J$5),2) -> 6.54 | L6: =RANK(K6,K$6:K$16,0) -> 6
A7: Austin, TX | B7: 7 | C7: 8 | D7: 2100 | E7: 8 | F7: 9 | G7: 4 | H7: 9 | I7: 6 | J7: 8 | K7: =ROUND(($B7*B$5)+($C7*C$5)+((10-(($D7-MIN($D$6:$D$16))/(MAX($D$6:$D$16)-MIN($D$6:$D$16))*9))*D$5)+($E7*E$5)+($F7*F$5)+((11-$G7)*G$5)+($H7*H$5)+($I7*I$5)+($J7*J$5),2) -> 7.16 | L7: =RANK(K7,K$6:K$16,0) -> 2
A8: Houston, TX | B8: 5 | C8: 8 | D8: 1700 | E8: 6 | F8: 8 | G8: 7 | H8: 7 | I8: 4 | J8: 7 | K8: =ROUND(($B8*B$5)+($C8*C$5)+((10-(($D8-MIN($D$6:$D$16))/(MAX($D$6:$D$16)-MIN($D$6:$D$16))*9))*D$5)+($E8*E$5)+($F8*F$5)+((11-$G8)*G$5)+($H8*H$5)+($I8*I$5)+($J8*J$5),2) -> 5.95 | L8: =RANK(K8,K$6:K$16,0) -> 9
A9: Research Triangle, NC | B9: 8 | C9: 9 | D9: 1650 | E9: 9 | F9: 8 | G9: 8 | H9: 9 | I9: 7 | J9: 8 | K9: =ROUND(($B9*B$5)+($C9*C$5)+((10-(($D9-MIN($D$6:$D$16))/(MAX($D$6:$D$16)-MIN($D$6:$D$16))*9))*D$5)+($E9*E$5)+($F9*F$5)+((11-$G9)*G$5)+($H9*H$5)+($I9*I$5)+($J9*J$5),2) -> 7.53 | L9: =RANK(K9,K$6:K$16,0) -> 1
A10: Charlotte, NC | B10: 7 | C10: 8 | D10: 1750 | E10: 7 | F10: 8 | G10: 7 | H10: 8 | I10: 7 | J10: 7 | K10: =ROUND(($B10*B$5)+($C10*C$5)+((10-(($D10-MIN($D$6:$D$16))/(MAX($D$6:$D$16)-MIN($D$6:$D$16))*9))*D$5)+($E10*E$5)+($F10*F$5)+((11-$G10)*G$5)+($H10*H$5)+($I10*I$5)+($J10*J$5),2) -> 6.81 | L10: =RANK(K10,K$6:K$16,0) -> 4
A11: Maryland/DC Metro | B11: 6 | C11: 9 | D11: 2400 | E11: 8 | F11: 9 | G11: 3 | H11: 9 | I11: 7 | J11: 8 | K11: =ROUND(($B11*B$5)+($C11*C$5)+((10-(($D11-MIN($D$6:$D$16))/(MAX($D$6:$D$16)-MIN($D$6:$D$16))*9))*D$5)+($E11*E$5)+($F11*F$5)+((11-$G11)*G$5)+($H11*H$5)+($I11*I$5)+($J11*J$5),2) -> 7.04 | L11: =RANK(K11,K$6:K$16,0) -> 3
A12: Central Florida (Orlando) | B12: 6 | C12: 7 | D12: 1800 | E12: 7 | F12: 7 | G12: 6 | H12: 7 | I12: 3 | J12: 7 | K12: =ROUND(($B12*B$5)+($C12*C$5)+((10-(($D12-MIN($D$6:$D$16))/(MAX($D$6:$D$16)-MIN($D$6:$D$16))*9))*D$5)+($E12*E$5)+($F12*F$5)+((11-$G12)*G$5)+($H12*H$5)+($I12*I$5)+($J12*J$5),2) -> 6.04 | L12: =RANK(K12,K$6:K$16,0) -> 8
A13: Philadelphia, PA | B13: 5 | C13: 8 | D13: 1950 | E13: 6 | F13: 7 | G13: 5 | H13: 7 | I13: 7 | J13: 7 | K13: =ROUND(($B13*B$5)+($C13*C$5)+((10-(($D13-MIN($D$6:$D$16))/(MAX($D$6:$D$16)-MIN($D$6:$D$16))*9))*D$5)+($E13*E$5)+($F13*F$5)+((11-$G13)*G$5)+($H13*H$5)+($I13*I$5)+($J13*J$5),2) -> 6.13 | L13: =RANK(K13,K$6:K$16,0) -> 7
A14: Nashville, TN | B14: 6 | C14: 8 | D14: 1900 | E14: 7 | F14: 8 | G14: 6 | H14: 8 | I14: 6 | J14: 9 | K14: =ROUND(($B14*B$5)+($C14*C$5)+((10-(($D14-MIN($D$6:$D$16))/(MAX($D$6:$D$16)-MIN($D$6:$D$16))*9))*D$5)+($E14*E$5)+($F14*F$5)+((11-$G14)*G$5)+($H14*H$5)+($I14*I$5)+($J14*J$5),2) -> 6.64 | L14: =RANK(K14,K$6:K$16,0) -> 5
A15: Memphis, TN | B15: 2 | C15: 5 | D15: 1100 | E15: 4 | F15: 5 | G15: 9 | H15: 4 | I15: 5 | J15: 4 | K15: =ROUND(($B15*B$5)+($C15*C$5)+((10-(($D15-MIN($D$6:$D$16))/(MAX($D$6:$D$16)-MIN($D$6:$D$16))*9))*D$5)+($E15*E$5)+($F15*F$5)+((11-$G15)*G$5)+($H15*H$5)+($I15*I$5)+($J15*J$5),2) -> 4.11 | L15: =RANK(K15,K$6:K$16,0) -> 11
A16: San Angelo, TX | B16: 5 | C16: 4 | D16: 950 | E16: 6 | F16: 3 | G16: 9 | H16: 2 | I16: 6 | J16: 3 | K16: =ROUND(($B16*B$5)+($C16*C$5)+((10-(($D16-MIN($D$6:$D$16))/(MAX($D$6:$D$16)-MIN($D$6:$D$16))*9))*D$5)+($E16*E$5)+($F16*F$5)+((11-$G16)*G$5)+($H16*H$5)+($I16*I$5)+($J16*J$5),2) -> 4.68 | L16: =RANK(K16,K$6:K$16,0) -> 10

Sheet Dashboard Summary
A1: Relocation Intelligence — Family Decision Summary
A2: Ranked by weighted family score. Safety (25%) and Healthcare (15%) are top weighted factors reflecting real family priorities.
A4: Rank | B4: City | C4: Weighted Score | D4: Family Strength | E4: Key Concern | F4: Rent Range | G4: Healthcare | H4: Verdict
A5: 1 | B5: Research Triangle, NC | C5: =IFERROR(VLOOKUP("Research Triangle, NC",'City Scoring Data'!$A$6:$K$16,10,0),"—") -> 8 | D5: Safety + top healthcare | E5: Rising demand | F5: $1,500-1,900 | G5: Excellent | H5: ✅ Top Pick
A6: 2 | B6: Charlotte, NC | C6: =IFERROR(VLOOKUP("Charlotte, NC",'City Scoring Data'!$A$6:$K$16,10,0),"—") -> 7 | D6: Balanced — strong safety | E6: Rapid growth | F6: $1,600-2,000 | G6: Strong | H6: ✅ Top Pick
A7: 3 | B7: Nashville, TN | C7: =IFERROR(VLOOKUP("Nashville, TN",'City Scoring Data'!$A$6:$K$16,10,0),"—") -> 9 | D7: Culture + remote friendly | E7: Crime trending up | F7: $1,700-2,100 | G7: Strong | H7: ✅ Heart says yes
A8: 4 | B8: Maryland/DC Metro | C8: =IFERROR(VLOOKUP("Maryland/DC Metro",'City Scoring Data'!$A$6:$K$16,10,0),"—") -> 8 | D8: Best healthcare density | E8: Very high COL | F8: $2,200-2,800 | G8: Excellent | H8: ⚠️ Budget check
A9: 5 | B9: Dallas-Fort Worth, TX | C9: =IFERROR(VLOOKUP("Dallas-Fort Worth, TX",'City Scoring Data'!$A$6:$K$16,10,0),"—") -> 7 | D9: Jobs + remote culture | E9: Traffic + sprawl | F9: $1,600-2,100 | G9: Strong | H9: ✅ Solid choice
A10: 6 | B10: Austin, TX | C10: =IFERROR(VLOOKUP("Austin, TX",'City Scoring Data'!$A$6:$K$16,10,0),"—") -> 8 | D10: Remote + job market | E10: COL rising fast | F10: $1,900-2,400 | G10: Strong | H10: ⚠️ Budget check
A11: 7 | B11: Central Florida (Orlando) | C11: =IFERROR(VLOOKUP("Central Florida (Orlando)",'City Scoring Data'!$A$6:$K$16,10,0),"—") -> 7 | D11: Cost balance | E11: Weather/hurricane risk | F11: $1,600-2,000 | G11: Moderate | H11: ⚠️ Research more
A12: 8 | B12: Houston, TX | C12: =IFERROR(VLOOKUP("Houston, TX",'City Scoring Data'!$A$6:$K$16,10,0),"—") -> 7 | D12: Affordability | E12: Flooding + safety | F12: $1,500-1,900 | G12: Strong | H12: ✅ Consider
A13: 9 | B13: Philadelphia, PA | C13: =IFERROR(VLOOKUP("Philadelphia, PA",'City Scoring Data'!$A$6:$K$16,10,0),"—") -> 7 | D13: Healthcare access | E13: Crime + high COL | F13: $1,700-2,200 | G13: Strong | H13: ⚠️ Research more
A14: 10 | B14: Memphis, TN | C14: =IFERROR(VLOOKUP("Memphis, TN",'City Scoring Data'!$A$6:$K$16,10,0),"—") -> 4 | D14: Low cost only | E14: Very high crime | F14: $900-1,300 | G14: Weak | H14: ❌ Not recommended
A15: 11 | B15: San Angelo, TX | C15: =IFERROR(VLOOKUP("San Angelo, TX",'City Scoring Data'!$A$6:$K$16,10,0),"—") -> 3 | D15: Familiar baseline | E15: Limited everything | F15: $800-1,100 | G15: Very Weak | H15: ❌ Baseline — leave

Sheet Priority Weights
A1: Family Priority Weights — Adjust to Reflect YOUR Priorities
A3: Category | B3: Weight | C3: Why It Matters for This Family | D3: Your Notes
A4: Safety & Family Security | B4: 25% | C4: Homeschool family — kids are home more. Crime + neighborhood safety = #1
A5: Healthcare Access | B5: 15% | C5: Pediatric specialty access critical. Distance to major children's hospital matters
A6: Cost of Living | B6: 10% | C6: Determines real purchasing power after rent
A7: Median Rent ($) | B7: 10% | C7: Direct monthly budget impact
A8: School Rating | B8: 10% | C8: Homeschool co-op community, resources, and legal environment by state
A9: Job Market | B9: 8% | C9: Remote-first — location less critical but local backup market matters
A10: Remote Work Culture | B10: 8% | C10: Coworking spaces, remote-friendly infrastructure, community
A11: Weather Risk | B11: 7% | C11: Severe weather disruption risk — especially with medical-complex child
A12: Cultural Fit | B12: 7% | C12: Long-term livability, community values, social integration
A13: TOTAL | B13: =SUM(B4:B12) -> 0 | C13: ✅ Must equal 100% for accurate scoring
